superspy/__init__.py
superspy/ast.py
superspy/code_source.py
superspy/language.py
superspy/system/arithmetic.py
superspy/system/base_language.py
superspy/system/braces.py
superspy/system/datatypes.py
superspy/system/flow_control.py
superspy/system/io.py
superspy/system/variables.py
superspy-0.3.14.dist-info/METADATA
superspy-0.3.14.dist-info/RECORD
superspy-0.3.14.dist-info/WHEEL
superspy-0.3.14.dist-info/top_level.txt
