Metadata-Version: 2.1
Name: superspy
Version: 0.3.14
Summary: Small Uncomplicated Plugin Extensible Reliable Shell in PYthon
Home-page: https://github.com/Kamik423/superspy
Author: Hans
Author-email: contact.kamik423@gmail.com
License: MIT
Platform: UNKNOWN
Classifier: Programming Language :: Python :: 3.7
Classifier: License :: OSI Approved :: MIT License
Classifier: Operating System :: OS Independent
Requires-Dist: pluginbase
